lins_log/__init__.py
lins_log/lins_log.py
lins_log/logs.py
lins_log/validacoes.py
lins_log-2.1.5.74.dist-info/METADATA
lins_log-2.1.5.74.dist-info/WHEEL
lins_log-2.1.5.74.dist-info/top_level.txt
lins_log-2.1.5.74.dist-info/RECORD
