Metadata-Version: 2.1
Name: lins-log
Version: 2.1.5.74
Summary: Para utilizar Graylog
Home-page: https://bitbucket.org/grupolinsferrao/pypck-logs/
Author: Nicollas Borges
Author-email: nicollasborges@lojaspompeia.com.br
License: MIT
Platform: UNKNOWN
Requires-Dist: graypy (==1.1.2)
